var bellstreet = {
"type": "FeatureCollection",
"crs": { "type": "name", "properties": { "name": "urn:ogc:def:crs:OGC:1.3:CRS84" } },
"features": [
{ "type": "Feature", "properties": { "id": 1, "descrip": "unc well" }, "geometry": { "type": "Point", "coordinates": [ -122.34756947, 47.61014621] } }
]
}
